pypular/__init__.py
pypular/__main__.py
pypular-0.2.dist-info/LICENSE
pypular-0.2.dist-info/METADATA
pypular-0.2.dist-info/WHEEL
pypular-0.2.dist-info/entry_points.txt
pypular-0.2.dist-info/top_level.txt
pypular-0.2.dist-info/RECORD
