Metadata-Version: 2.1
Name: pypular
Version: 0.2
Summary: Increase the popularity of your PYPI package by downloading it many times.
Home-page: https://codeberg.org/ltworf/pypular/
Author: Salvo 'LtWorf' Tomaselli
Author-email: Salvo 'LtWorf' Tomaselli <tiposchi@tiscali.it>
License: GNU AFFERO GENERAL PUBLIC LICENSE
Project-URL: Homepage, https://codeberg.org/ltworf/pypular/
Project-URL: Bug Tracker, https://codeberg.org/ltworf/pypular//issues
Keywords: pypi,counter,popularity
Classifier: Development Status :: 2 - Pre-Alpha
Classifier: Environment :: Console
Classifier: License :: OSI Approved :: GNU Affero General Public License v3
Classifier: Programming Language :: Python :: 3.11
Classifier: Programming Language :: Python :: 3.12
Requires-Python: >=3.11
License-File: LICENSE
